{
  "disease": "النقرس",
  "department": "طب العظام",
  "definition": "النقرس هو شكل معقد من التهاب المفاصل يحدث عند تراكم بلورات حمض اليوريك في المفاصل، مما يؤدي إلى نوبات ألم مفاجئة، تورم، واحمرار في المفاصل، غالبًا في إصبع القدم الأكبر.",
  "symptoms": [
    "ألم شديد في المفاصل، خصوصًا إصبع القدم الكبير",
    "الشعور بعدم الراحة في المفاصل بعد انتهاء النوبة",
    "تورم واحمرار المفصل المصاب",
    "حرارة المفصل المصاب عند اللمس",
    "محدودية نطاق الحركة في المفصل المصاب"
  ],
  "Causes": [
    "تراكم بلورات حمض اليوريك في المفاصل",
    "ارتفاع مستويات حمض اليوريك في الدم بسبب تحلل البورينات",
    "تناول أطعمة غنية بالبورينات مثل اللحوم الحمراء، الأحشاء الداخلية، والمأكولات البحرية",
    "تناول الكحوليات، خاصة الجعة، والمشروبات المحلاة بالفركتوز",
    "قصور الكلى في التخلص من حمض اليوريك"
  ],
  "risk_factors": [
    "النظام الغذائي الغني بالبورينات والكحوليات",
    "زيادة وزن الجسم",
    "أمراض مزمنة مثل ارتفاع ضغط الدم، داء السكري، السمنة، متلازمة الأيض، وأمراض القلب والكلى",
    "تناول أدوية معينة مثل المدرات الثيازيدية، مثبطات ACE، حاصرات بيتا، بعض أدوية منع رفض الأعضاء",
    "التاريخ العائلي للإصابة بالنقرس",
    "الجنس والعمر (أكثر شيوعًا عند الرجال بين 30-50 سنة، وعند النساء بعد انقطاع الطمث)",
    "العمليات الجراحية أو الإصابات الحديثة"
  ],
  "complications": [
    "النقرس المتكرر: تكرار النوبات وقد يؤدي لتآكل المفاصل إذا لم يُعالج",
    "النقرس المتقدم: تكون رواسب بلورات اليورات تحت الجلد (توفي)",
    "حصوات الكلى الناتجة عن تراكم اليورات في المسالك البولية"
  ],
  "prevention": [
    "اتباع نظام غذائي منخفض البورينات والكحوليات",
    "المحافظة على وزن صحي",
    "السيطرة على الأمراض المزمنة المصاحبة مثل ارتفاع ضغط الدم والسكري",
    "شرب كميات كافية من الماء للمساعدة في التخلص من حمض اليوريك",
    "استخدام الأدوية الوقائية حسب وصف الطبيب لمنع تكرار النوبات"
  ],
  "diagnosis": [
    "تحليل دم لقياس مستويات حمض اليوريك",
    "تحليل سائل المفصل لتحديد وجود بلورات اليورات",
    "الأدوية المضادة للالتهاب غير الستيرويدية (NSAIDs) لتخفيف الألم",
    "الكولشيسين لعلاج نوبات النقرس الحادة",
    "أدوية خافضة لحمض اليوريك لمنع تراكم اليورات على المدى الطويل",
    "العلاجات الداعمة مثل الراحة، الكمادات الباردة، ورفع المفصل المصاب"
  ]
}
