{
  "disease": "الأورام الرباطية (الأورام الجسدية)",
  "department": "الأورام",
  "definition": "أورام غير سرطانية تحدث في النسيج الضام، غالبًا في البطن، الذراعين، والساقين. يمكن أن تكون عدوانية وتتصرف مثل السرطانات لكنها لا تنتشر في مناطق أخرى من الجسم. تُعرف أحيانًا بالورم الليفي الشرس.",
  "symptoms": [
    "كتلة أو منطقة متورمة",
    "الشعور بالألم",
    "فقدان الوظيفة في المنطقة المصابة",
    "تقلصات مؤلمة وغثيان عند حدوث الأورام في البطن"
  ],
  "causes": [
    "تغيرات في الحمض النووي لخلايا النسيج الضام تؤدي إلى تكاثر سريع وتكوين كتلة (الورم) التي قد تغزو الأنسجة السليمة"
  ],
  "risk_factors": [
    "عمر الشباب (20–30 سنة)",
    "متلازمة وراثية تسبب العديد من السلائل القولونية، مثل السلائل الورمي الغدي العائلي",
    "الحمل (في حالات نادرة)",
    "الإصابة أو الجراحة السابقة في المنطقة"
  ],
  "prevention": [
    "لا توجد وسيلة مؤكدة للوقاية من الأورام الرباطية"
  ],
  "treatment": [
    "الجراحة",
    "المعالجة الإشعاعية",
    "العلاج الكيميائي",
    "أدوية أخرى حسب تقييم الطبيب"
  ]
}
