{
  "disease": "خلل التنسج العضلي الليفي",
  "department": "أمراض القلب",
  "definition": "خلل التنسج العضلي الليفي هو حالة مرضية تسبب تضيقًا وتوسعًا للشرايين متوسطة الحجم في الجسم، مما يقلل من تدفق الدم ويؤثر على وظيفة الأعضاء المختلفة، خاصة الكليتين والدماغ، وأحيانًا القدمين والقلب والبطن والذراعين.",
  "types": [
    {
      "name": "خلل التنسج العضلي الليفي الكلوي",
      "description": "يصيب الشرايين التي تغذي الكليتين، مما قد يؤدي إلى ارتفاع ضغط الدم ومشكلات في وظائف الكلى."
    },
    {
      "name": "خلل التنسج العضلي الليفي الدماغي",
      "description": "يصيب الشرايين الدماغية، وقد يسبب صداعًا، ودوخة، وطنين الأذن، وأعراض السكتة الدماغية أو نوبة إقفارية عابرة."
    },
    {
      "name": "خلل التنسج العضلي الليفي التاجي",
      "description": "يصيب الشرايين التاجية في القلب، وقد يؤدي إلى تمزق الشريان التاجي التلقائي (SCAD) واضطرابات قلبية خطيرة."
    },
    {
      "name": "خلل التنسج العضلي الليفي الطرفي",
      "description": "يصيب الشرايين في القدمين أو الذراعين، ويؤثر على تدفق الدم الطرفي في حالات نادرة."
    }
  ],
  "symptoms": [
    "ارتفاع ضغط الدم",
    "مشكلات في وظائف الكلى",
    "صداع",
    "طنين الأذن",
    "دوخة",
    "ألم مفاجئ في الرقبة",
    "أعراض السكتة الدماغية مثل ضعف في الذراعين أو الساقين",
    "تغيرات مفاجئة في الرؤية أو القدرة على الكلام"
  ],
  "risk_factors": [
    "النساء أكثر عرضة من الرجال",
    "التقدم في العمر، غالبًا في الخمسينيات",
    "التدخين",
    "تاريخ عائلي للحالة في بعض الحالات"
  ],
  "diagnosis": [
    "الفحص السريري",
    "الأشعة المقطعية أو التصوير بالرنين المغناطيسي للشرايين",
    "تصوير الأوعية الدموية باستخدام القسطرة أو الأشعة التداخلية",
    "قياس ضغط الدم والكشف عن مضاعفات الأعضاء المتأثرة"
  ],
  "treatment": [
    "إدارة ضغط الدم والأعراض المصاحبة",
    "الأدوية للتحكم في ارتفاع ضغط الدم أو مضادات التخثر عند الحاجة",
    "تدخلات جراحية أو تداخلية لإصلاح الشرايين المتضررة",
    "المتابعة الدورية للكشف عن مضاعفات مثل تمدد أو تمزق الشرايين"
  ],
  "complications": [
    "ارتفاع ضغط الدم المزمن",
    "تمزق جدران الشرايين (التسلخ)",
    "تمدد الأوعية الدموية",
    "السكتة الدماغية",
    "مشكلات القلب أو فشل القلب عند تأثر الشرايين التاجية"
  ],
  "prevention": [
    "التحكم في ضغط الدم",
    "تجنب التدخين",
    "المتابعة الطبية الدورية للكشف المبكر عن مضاعفات",
    "الحفاظ على نمط حياة صحي يقلل من عوامل الخطر القلبية والوعائية"
  ],
  "Causes": [
    "تغيرات جينية محتملة",
    "دور محتمل للهرمونات الأنثوية",
    "سبب دقيق غير معروف بالكامل"
  ]
}
