{
  "disease": "اضطراب الأعراض الجسدية",
  "department": "أمراض الصدر",
  "definition": "حالة تركز فيها على الأعراض الجسدية مثل الألم أو التعب بشكل مفرط، مما يسبب أذًى عاطفيًا كبيرًا ومشاكل وظيفية. قد يكون لديك حالة طبية مشخَّصة أخرى أو لا، لكن رد فعلك على الأعراض غير طبيعي ويؤثر على حياتك اليومية.",
  "symptoms": [
    "ألم أو ضيق في التنفس",
    "تعب أو وهن شديد",
    "قلق مستمر بشأن المرض المحتمل",
    "الخوف من خطورة الأعراض رغم عدم وجود دليل",
    "الفحص المتكرر للجسد بحثًا عن أي تغييرات",
    "زيارات متكررة للعناية الصحية دون طمأنة"
  ],
  "Causes": [
    "عوامل جينية وبيولوجية مثل زيادة الحساسية للألم",
    "التأثير العائلي والبيئي",
    "سمة شخصية سلبية تؤثر في إدراك المرض والأعراض",
    "نقص الوعي أو صعوبة معالجة العواطف",
    "سلوكيات مكتسبة من الانتباه أو التجارب السابقة المرتبطة بالأعراض"
  ],
  "risk_factors": [
    "القلق أو الاكتئاب",
    "وجود حالة طبية حالية أو التعافي من واحدة",
    "تاريخ عائلي قوي للإصابة بأمراض معينة",
    "التعرض لأحداث حياة مجهدة أو صدمة",
    "تعليم أو وضع اجتماعي واقتصادي منخفض"
  ],
  "complications": [
    "ضعف الجسم وتراجع الصحة العامة",
    "صعوبة في تأدية الأنشطة اليومية المعتادة",
    "مشاكل في العلاقات الاجتماعية",
    "مشاكل في العمل أو بطالة",
    "اضطرابات عقلية أخرى مثل القلق والاكتئاب واضطرابات الشخصية",
    "زيادة احتمالية الإقدام على الانتحار بسبب الاكتئاب",
    "مشاكل مالية نتيجة كثرة التردد على الأطباء"
  ],
  "prevention": [
    "طلب الدعم من المختصين عند وجود قلق أو اكتئاب",
    "ممارسة أساليب إدارة الإجهاد والاسترخاء بانتظام",
    "الحصول على العلاج مبكرًا لتقليل تفاقم الأعراض",
    "الالتزام بخطة العلاج للحد من الانتكاسات أو سوء الأعراض"
  ]
}
