{
  "disease": "اضطراب المعالجة السمعية",
  "department": "طب الأعصاب",
  "definition": "نوع من فقدان السمع يحدث بسبب تأثير على الجزء من الدماغ الذي يعالج الأصوات، مما يؤثر على قدرة الشخص على فهم ما يسمعه. يُعرف أيضًا باسم اضطراب المعالجة السمعية المركزية (CAPD).",
  "symptoms": [
    "صعوبة معرفة مصدر الصوت",
    "صعوبة فهم الكلمات المنطوقة بسرعة أو في بيئة صاخبة",
    "مشكلات في الانتباه",
    "مشكلات في القراءة والتهجئة",
    "صعوبة اتباع التعليمات المعقدة",
    "صعوبة تعلم لغة جديدة",
    "صعوبة الغناء أو الاستمتاع بالموسيقى",
    "صعوبة تذكر المعلومات المسموعة",
    "تأخر الرد على المتحدث",
    "الحاجة لتكرار الكلام من الآخرين",
    "صعوبة فهم السخرية أو النكات"
  ],
  "causes": [
    "غير معروف في كثير من الحالات",
    "السكتة الدماغية وإصابة الرأس لدى البالغين الأكبر سنًا",
    "مشكلات عند الولادة مثل الولادة المبكرة أو انخفاض الوزن",
    "عدوى الأذن المتكررة في الطفولة"
  ],
  "risk_factors": [
    "التقدم في العمر",
    "السكتة الدماغية",
    "إصابة الرأس",
    "التسمم بالرصاص",
    "اضطرابات نوبات الصرع",
    "المشكلات المرتبطة بالولادة",
    "عدوى الأذن المتكررة في عمر مبكر"
  ],
  "prevention": [
    "الوقاية من عدوى الأذن المتكررة للأطفال",
    "الاعتناء بالسلامة لتجنب إصابات الرأس",
    "تجنب التعرض للمواد السامة مثل الرصاص والكحول والمخدرات أثناء الحمل"
  ]
}
