{
  "disease": "ألم الفك، اللثة أو الأسنان",
  "department": "طب الأسنان",
  "description": "دليل مخصص للأشخاص الذين يعانون من ألم في الفك، اللثة أو الأسنان، لتقديم معلومات أثناء انتظار تشخيص طبيب الأسنان أو مختص صحة آخر.",
  "symptoms": [
    "ألم في الفك",
    "ألم في اللثة",
    "ألم في الأسنان"
  ],
  "risk_factors": [
    "قد يكون ألم الفك أحيانًا عرضًا للذبحة الصدرية أو نوبة قلبية"
  ],
  "diagnosis": "الفحص السريري من قبل طبيب الأسنان أو مختص صحة الفم، مع مراجعة التاريخ الطبي للمريض.",
  "treatment": "تقديم معلومات لتخفيف الأعراض أثناء انتظار التشخيص، أو اتباع العلاج الذي يحدده الطبيب.",
  "complications": "قد توجد أكثر من حالة في الوقت نفسه. الألم الشديد أو المفاجئ قد يشير إلى حالة طبية عاجلة.",
  "prevention": "الحصول على رعاية عاجلة عند وجود أعراض خطيرة. لا يغني عن الفحص المباشر عند الطبيب."
}