{
  "disease": "التهاب الكبد A",
  "department": "أمراض الجهاز الهضمي",
  "definition": "التهاب الكبد A هو إصابة شديدة العدوى تصيب الكبد بسبب فيروس التهاب الكبد A، ويؤثر على قدرة الكبد على العمل بشكل طبيعي. غالبًا ما يحدث نتيجة تناول طعام أو شراب ملوث أو المخالطة اللصيقة لشخص مصاب، ويتعافى معظم المرضى دون ضرر دائم.",
  "symptoms": [
    "إرهاق وضعف غير معتاد",
    "غثيان وقيء وإسهال مفاجئ",
    "ألم أو انزعاج في البطن، خاصة في الجزء العلوي الأيمن",
    "براز شاحب أو رمادي اللون",
    "فقدان الشهية",
    "حمى خفيفة",
    "بول داكن",
    "ألم المفاصل",
    "اصفرار الجلد وبياض العينين (اليرقان)",
    "حكة شديدة"
  ],
  "Causes": [
    "فيروس التهاب الكبد A الذي يصيب خلايا الكبد ويسبب الالتهاب",
    "انتقال الفيروس عن طريق المسار الفموي البرازي، مثل تناول طعام أو شرب ماء ملوث بالبراز المصاب",
    "المخالطة اللصيقة لشخص حامل للفيروس",
    "الاتصال الجنسي مع شخص مصاب"
  ],
  "risk_factors": [
    "السفر أو العمل في مناطق ينتشر فيها التهاب الكبد A",
    "الإقامة مع شخص مصاب بالمرض",
    "الرجال الذين يمارسون الجنس مع رجال آخرين",
    "الإصابة بفيروس نقص المناعة البشري",
    "التشرد",
    "تعاطي أي نوع من المخدرات الترفيهية"
  ],
  "diagnosis": [
    "تقييم الأعراض السريرية",
    "اختبارات الدم للكشف عن فيروس التهاب الكبد A"
  ],
  "treatment": [
    "لا حاجة لعلاج محدد في معظم الحالات المعتدلة",
    "الراحة، التغذية السليمة، وتعويض السوائل حسب الحاجة"
  ],
  "complications": [
    "نادراً ما يؤدي إلى فشل كبدي حاد، خاصة لدى كبار السن أو المصابين بأمراض كبد مزمنة",
    "قد يتطلب الفشل الكبدي الحاد دخول المستشفى أو زراعة الكبد"
  ],
  "prevention": [
    "تلقي لقاح التهاب الكبد A (حقنتان أو ثلاثة إذا كان مختلط مع لقاح التهاب الكبد B)",
    "غسل اليدين بشكل متكرر",
    "تجنب الطعام أو الماء الملوث",
    "تجنب الأطعمة غير المطهية جيدًا أو النيئة",
    "اتباع ممارسات صحية جيدة أثناء السفر"
  ]
}
