{
  "disease": "سرطان الشرج",
  "department": "الأورام",
  "definition": "سرطان الشرج هو نمو غير طبيعي للخلايا يبدأ في القناة الشرجية، وهي الأنبوب القصير في نهاية المستقيم الذي يمر عبره البراز عند خروجه من الجسم. يبدأ المرض عندما تتغير الـDNA في الخلايا داخل القناة الشرجية، مما يؤدي إلى نموها بشكل غير منضبط وتكوّن ورم سرطاني.",
  "types": [
    "سرطان الخلايا الحرشفية (الأكثر شيوعًا) يبدأ في خلايا القناة الشرجية والخلايا المسطحة حول الشرج.",
    "السرطان الغدي يبدأ في الغدد التي تنتج المخاط.",
    "سرطان الخلايا العصبية الصمّاء (عدواني ونادر).",
    "سرطان الخلايا القاعدية النادر جدًا في الجلد حول الشرج.",
    "الورم الميلانيني، وهو نادر ومرتبط بخلايا الميلانين."
  ],
  "symptoms": [
    "نزف من الشرج أو المستقيم.",
    "وجود دم في البراز.",
    "ألم في منطقة الشرج.",
    "وجود نتوء أو ورم في قناة الشرج.",
    "حكة في منطقة الشرج.",
    "الاضطرار إلى الذهاب إلى دورة المياه كثيرًا."
  ],
  "risk_factors": [
    "التعرّض لفيروس الورم الحليمي البشري (HPV) عالي الخطورة.",
    "ممارسة الجنس الشرجي وزيادة عدد الشركاء الجنسيين يزيدان الخطر.",
    "التدخين.",
    "ضعف الجهاز المناعي بسبب أدوية أو حالات صحية مثل فيروس نقص المناعة البشرية.",
    "وجود تاريخ مرضي لبعض سرطانات الأعضاء التناسلية."
  ],
  "Causes": "يحدث سرطان الشرج عندما تطرأ تغييرات في الحمض النووي داخل خلايا القناة الشرجية، وتؤدي تلك التغييرات إلى نمو غير طبيعي للخلايا وتكاثرها بشكل غير منضبط، مما يكوّن ورمًا سرطانيًا. غالبًا ما يكون الفيروس الورم الحليمي البشري (HPV) عاملًا مساهمًا في الإصابة.",
  "diagnosis": [
    "الفحص السريري من قبل مقدم الرعاية الصحية مع تقييم الأعراض.",
    "الفحوصات التصويرية مثل الأشعة المقطعية أو الرنين المغناطيسي أو PET.",
    "الخزعة لأخذ عيّنة من الأنسجة وتحليلها مخبريًا لتأكيد التشخيص."
  ]
}
